setup.py
lib/crtomo_bin_wrapper/__init__.py
lib/crtomo_bin_wrapper/binaries/CRMod_stable
lib/crtomo_bin_wrapper/binaries/CRTomo_stable
lib/crtomo_bin_wrapper/binaries/CutMcK_stable
src/CRMod.py
src/CRTomo.py
src/CutMcK.py
src/crtomo_bin_wrapper.egg-info/PKG-INFO
src/crtomo_bin_wrapper.egg-info/SOURCES.txt
src/crtomo_bin_wrapper.egg-info/dependency_links.txt
src/crtomo_bin_wrapper.egg-info/entry_points.txt
src/crtomo_bin_wrapper.egg-info/top_level.txt